{
    "course_podcasts": [
        {
            "lecture_num": 1,
            "date": "04/01/2019",
            "audio_url": "https://podcast.ucsd.edu/Podcasts//sp19/cse20_b00_o6k37uiu6t/cse20_b00-04012019-0900.mp3",
            "video_url": "https://podcast.ucsd.edu/Podcasts//sp19/cse20_b00_o6k37uiu6t/cse20_b00-04012019-0900.mp4",
            "professor": "Politz, Joseph Gibbs",
            "quarter": "Spring 2019",
            "course_name": "Intro/Discrete Mathematics",
            "department": "CSE",
            "course_num": "20",
            "section_id": "B00"
        },
        {
            "lecture_num": 2,
            "date": "04/03/2019",
            "audio_url": "https://podcast.ucsd.edu/Podcasts//sp19/cse20_b00_o6k37uiu6t/cse20_b00-04032019-0900.mp3",
            "video_url": "https://podcast.ucsd.edu/Podcasts//sp19/cse20_b00_o6k37uiu6t/cse20_b00-04032019-0900.mp4",
            "professor": "Politz, Joseph Gibbs",
            "quarter": "Spring 2019",
            "course_name": "Intro/Discrete Mathematics",
            "department": "CSE",
            "course_num": "20",
            "section_id": "B00"
        },
        {
            "lecture_num": 3,
            "date": "04/05/2019",
            "audio_url": "https://podcast.ucsd.edu/Podcasts//sp19/cse20_b00_o6k37uiu6t/cse20_b00-04052019-0900.mp3",
            "video_url": "https://podcast.ucsd.edu/Podcasts//sp19/cse20_b00_o6k37uiu6t/cse20_b00-04052019-0900.mp4",
            "professor": "Politz, Joseph Gibbs",
            "quarter": "Spring 2019",
            "course_name": "Intro/Discrete Mathematics",
            "department": "CSE",
            "course_num": "20",
            "section_id": "B00"
        },
        {
            "lecture_num": 4,
            "date": "04/08/2019",
            "audio_url": "https://podcast.ucsd.edu/Podcasts//sp19/cse20_b00_o6k37uiu6t/cse20_b00-04082019-0900.mp3",
            "video_url": "https://podcast.ucsd.edu/Podcasts//sp19/cse20_b00_o6k37uiu6t/cse20_b00-04082019-0900.mp4",
            "professor": "Politz, Joseph Gibbs",
            "quarter": "Spring 2019",
            "course_name": "Intro/Discrete Mathematics",
            "department": "CSE",
            "course_num": "20",
            "section_id": "B00"
        },
        {
            "lecture_num": 5,
            "date": "04/10/2019",
            "audio_url": "https://podcast.ucsd.edu/Podcasts//sp19/cse20_b00_o6k37uiu6t/cse20_b00-04102019-0900.mp3",
            "video_url": "https://podcast.ucsd.edu/Podcasts//sp19/cse20_b00_o6k37uiu6t/cse20_b00-04102019-0900.mp4",
            "professor": "Politz, Joseph Gibbs",
            "quarter": "Spring 2019",
            "course_name": "Intro/Discrete Mathematics",
            "department": "CSE",
            "course_num": "20",
            "section_id": "B00"
        },
        {
            "lecture_num": 6,
            "date": "04/12/2019",
            "audio_url": "https://podcast.ucsd.edu/Podcasts//sp19/cse20_b00_o6k37uiu6t/cse20_b00-04122019-0900.mp3",
            "video_url": "https://podcast.ucsd.edu/Podcasts//sp19/cse20_b00_o6k37uiu6t/cse20_b00-04122019-0900.mp4",
            "professor": "Politz, Joseph Gibbs",
            "quarter": "Spring 2019",
            "course_name": "Intro/Discrete Mathematics",
            "department": "CSE",
            "course_num": "20",
            "section_id": "B00"
        },
        {
            "lecture_num": 7,
            "date": "04/15/2019",
            "audio_url": "https://podcast.ucsd.edu/Podcasts//sp19/cse20_b00_o6k37uiu6t/cse20_b00-04152019-0900.mp3",
            "video_url": "https://podcast.ucsd.edu/Podcasts//sp19/cse20_b00_o6k37uiu6t/cse20_b00-04152019-0900.mp4",
            "professor": "Politz, Joseph Gibbs",
            "quarter": "Spring 2019",
            "course_name": "Intro/Discrete Mathematics",
            "department": "CSE",
            "course_num": "20",
            "section_id": "B00"
        },
        {
            "lecture_num": 8,
            "date": "04/17/2019",
            "audio_url": "https://podcast.ucsd.edu/Podcasts//sp19/cse20_b00_o6k37uiu6t/cse20_b00-04172019-0900.mp3",
            "video_url": "https://podcast.ucsd.edu/Podcasts//sp19/cse20_b00_o6k37uiu6t/cse20_b00-04172019-0900.mp4",
            "professor": "Politz, Joseph Gibbs",
            "quarter": "Spring 2019",
            "course_name": "Intro/Discrete Mathematics",
            "department": "CSE",
            "course_num": "20",
            "section_id": "B00"
        },
        {
            "lecture_num": 9,
            "date": "04/19/2019",
            "audio_url": "https://podcast.ucsd.edu/Podcasts//sp19/cse20_b00_o6k37uiu6t/cse20_b00-04192019-0900.mp3",
            "video_url": "https://podcast.ucsd.edu/Podcasts//sp19/cse20_b00_o6k37uiu6t/cse20_b00-04192019-0900.mp4",
            "professor": "Politz, Joseph Gibbs",
            "quarter": "Spring 2019",
            "course_name": "Intro/Discrete Mathematics",
            "department": "CSE",
            "course_num": "20",
            "section_id": "B00"
        },
        {
            "lecture_num": 10,
            "date": "04/22/2019",
            "audio_url": "https://podcast.ucsd.edu/Podcasts//sp19/cse20_b00_o6k37uiu6t/cse20_b00-04222019-0900.mp3",
            "video_url": "https://podcast.ucsd.edu/Podcasts//sp19/cse20_b00_o6k37uiu6t/cse20_b00-04222019-0900.mp4",
            "professor": "Politz, Joseph Gibbs",
            "quarter": "Spring 2019",
            "course_name": "Intro/Discrete Mathematics",
            "department": "CSE",
            "course_num": "20",
            "section_id": "B00"
        },
        {
            "lecture_num": 11,
            "date": "04/24/2019",
            "audio_url": "https://podcast.ucsd.edu/Podcasts//sp19/cse20_b00_o6k37uiu6t/cse20_b00-04242019-0900.mp3",
            "video_url": "https://podcast.ucsd.edu/Podcasts//sp19/cse20_b00_o6k37uiu6t/cse20_b00-04242019-0900.mp4",
            "professor": "Politz, Joseph Gibbs",
            "quarter": "Spring 2019",
            "course_name": "Intro/Discrete Mathematics",
            "department": "CSE",
            "course_num": "20",
            "section_id": "B00"
        },
        {
            "lecture_num": 12,
            "date": "04/26/2019",
            "audio_url": "https://podcast.ucsd.edu/Podcasts//sp19/cse20_b00_o6k37uiu6t/cse20_b00-04262019-0900.mp3",
            "video_url": "https://podcast.ucsd.edu/Podcasts//sp19/cse20_b00_o6k37uiu6t/cse20_b00-04262019-0900.mp4",
            "professor": "Politz, Joseph Gibbs",
            "quarter": "Spring 2019",
            "course_name": "Intro/Discrete Mathematics",
            "department": "CSE",
            "course_num": "20",
            "section_id": "B00"
        },
        {
            "lecture_num": 13,
            "date": "04/29/2019",
            "audio_url": "https://podcast.ucsd.edu/Podcasts//sp19/cse20_b00_o6k37uiu6t/cse20_b00-04292019-0900.mp3",
            "video_url": "https://podcast.ucsd.edu/Podcasts//sp19/cse20_b00_o6k37uiu6t/cse20_b00-04292019-0900.mp4",
            "professor": "Politz, Joseph Gibbs",
            "quarter": "Spring 2019",
            "course_name": "Intro/Discrete Mathematics",
            "department": "CSE",
            "course_num": "20",
            "section_id": "B00"
        },
        {
            "lecture_num": 14,
            "date": "05/01/2019",
            "audio_url": "https://podcast.ucsd.edu/Podcasts//sp19/cse20_b00_o6k37uiu6t/cse20_b00-05012019-0900.mp3",
            "video_url": "https://podcast.ucsd.edu/Podcasts//sp19/cse20_b00_o6k37uiu6t/cse20_b00-05012019-0900.mp4",
            "professor": "Politz, Joseph Gibbs",
            "quarter": "Spring 2019",
            "course_name": "Intro/Discrete Mathematics",
            "department": "CSE",
            "course_num": "20",
            "section_id": "B00"
        },
        {
            "lecture_num": 15,
            "date": "05/03/2019",
            "audio_url": "https://podcast.ucsd.edu/Podcasts//sp19/cse20_b00_o6k37uiu6t/cse20_b00-05032019-0900.mp3",
            "video_url": "https://podcast.ucsd.edu/Podcasts//sp19/cse20_b00_o6k37uiu6t/cse20_b00-05032019-0900.mp4",
            "professor": "Politz, Joseph Gibbs",
            "quarter": "Spring 2019",
            "course_name": "Intro/Discrete Mathematics",
            "department": "CSE",
            "course_num": "20",
            "section_id": "B00"
        },
        {
            "lecture_num": 16,
            "date": "05/06/2019",
            "audio_url": "https://podcast.ucsd.edu/Podcasts//sp19/cse20_b00_o6k37uiu6t/cse20_b00-05062019-0900.mp3",
            "video_url": "https://podcast.ucsd.edu/Podcasts//sp19/cse20_b00_o6k37uiu6t/cse20_b00-05062019-0900.mp4",
            "professor": "Politz, Joseph Gibbs",
            "quarter": "Spring 2019",
            "course_name": "Intro/Discrete Mathematics",
            "department": "CSE",
            "course_num": "20",
            "section_id": "B00"
        },
        {
            "lecture_num": 17,
            "date": "05/08/2019",
            "audio_url": "https://podcast.ucsd.edu/Podcasts//sp19/cse20_b00_o6k37uiu6t/cse20_b00-05082019-0900.mp3",
            "video_url": "https://podcast.ucsd.edu/Podcasts//sp19/cse20_b00_o6k37uiu6t/cse20_b00-05082019-0900.mp4",
            "professor": "Politz, Joseph Gibbs",
            "quarter": "Spring 2019",
            "course_name": "Intro/Discrete Mathematics",
            "department": "CSE",
            "course_num": "20",
            "section_id": "B00"
        },
        {
            "lecture_num": 18,
            "date": "05/10/2019",
            "audio_url": "https://podcast.ucsd.edu/Podcasts//sp19/cse20_b00_o6k37uiu6t/cse20_b00-05102019-0900.mp3",
            "video_url": "https://podcast.ucsd.edu/Podcasts//sp19/cse20_b00_o6k37uiu6t/cse20_b00-05102019-0900.mp4",
            "professor": "Politz, Joseph Gibbs",
            "quarter": "Spring 2019",
            "course_name": "Intro/Discrete Mathematics",
            "department": "CSE",
            "course_num": "20",
            "section_id": "B00"
        },
        {
            "lecture_num": 19,
            "date": "05/13/2019",
            "audio_url": "https://podcast.ucsd.edu/Podcasts//sp19/cse20_b00_o6k37uiu6t/cse20_b00-05132019-0900.mp3",
            "video_url": "https://podcast.ucsd.edu/Podcasts//sp19/cse20_b00_o6k37uiu6t/cse20_b00-05132019-0900.mp4",
            "professor": "Politz, Joseph Gibbs",
            "quarter": "Spring 2019",
            "course_name": "Intro/Discrete Mathematics",
            "department": "CSE",
            "course_num": "20",
            "section_id": "B00"
        },
        {
            "lecture_num": 20,
            "date": "05/15/2019",
            "audio_url": "https://podcast.ucsd.edu/Podcasts//sp19/cse20_b00_o6k37uiu6t/cse20_b00-05152019-0900.mp3",
            "video_url": "https://podcast.ucsd.edu/Podcasts//sp19/cse20_b00_o6k37uiu6t/cse20_b00-05152019-0900.mp4",
            "professor": "Politz, Joseph Gibbs",
            "quarter": "Spring 2019",
            "course_name": "Intro/Discrete Mathematics",
            "department": "CSE",
            "course_num": "20",
            "section_id": "B00"
        },
        {
            "lecture_num": 21,
            "date": "05/17/2019",
            "audio_url": "https://podcast.ucsd.edu/Podcasts//sp19/cse20_b00_o6k37uiu6t/cse20_b00-05172019-0900.mp3",
            "video_url": "https://podcast.ucsd.edu/Podcasts//sp19/cse20_b00_o6k37uiu6t/cse20_b00-05172019-0900.mp4",
            "professor": "Politz, Joseph Gibbs",
            "quarter": "Spring 2019",
            "course_name": "Intro/Discrete Mathematics",
            "department": "CSE",
            "course_num": "20",
            "section_id": "B00"
        },
        {
            "lecture_num": 22,
            "date": "05/20/2019",
            "audio_url": "https://podcast.ucsd.edu/Podcasts//sp19/cse20_b00_o6k37uiu6t/cse20_b00-05202019-0900.mp3",
            "video_url": "https://podcast.ucsd.edu/Podcasts//sp19/cse20_b00_o6k37uiu6t/cse20_b00-05202019-0900.mp4",
            "professor": "Politz, Joseph Gibbs",
            "quarter": "Spring 2019",
            "course_name": "Intro/Discrete Mathematics",
            "department": "CSE",
            "course_num": "20",
            "section_id": "B00"
        },
        {
            "lecture_num": 23,
            "date": "05/22/2019",
            "audio_url": "https://podcast.ucsd.edu/Podcasts//sp19/cse20_b00_o6k37uiu6t/cse20_b00-05222019-0900.mp3",
            "video_url": "https://podcast.ucsd.edu/Podcasts//sp19/cse20_b00_o6k37uiu6t/cse20_b00-05222019-0900.mp4",
            "professor": "Politz, Joseph Gibbs",
            "quarter": "Spring 2019",
            "course_name": "Intro/Discrete Mathematics",
            "department": "CSE",
            "course_num": "20",
            "section_id": "B00"
        },
        {
            "lecture_num": 24,
            "date": "05/24/2019",
            "audio_url": "https://podcast.ucsd.edu/Podcasts//sp19/cse20_b00_o6k37uiu6t/cse20_b00-05242019-0900.mp3",
            "video_url": "https://podcast.ucsd.edu/Podcasts//sp19/cse20_b00_o6k37uiu6t/cse20_b00-05242019-0900.mp4",
            "professor": "Politz, Joseph Gibbs",
            "quarter": "Spring 2019",
            "course_name": "Intro/Discrete Mathematics",
            "department": "CSE",
            "course_num": "20",
            "section_id": "B00"
        }
    ],
    "num_podcasts": 24,
    "podcast_course_metadata": {
        "course_name": "Intro/Discrete Mathematics",
        "department": "CSE",
        "course_num": "20",
        "section_id": "B00"
    }
}